msdLib/__init__.py
msdLib/data_processing.py
msdLib/model_training.py
msdLib/utils.py
missedSampleLib-0.0.3.dist-info/METADATA
missedSampleLib-0.0.3.dist-info/WHEEL
missedSampleLib-0.0.3.dist-info/license
missedSampleLib-0.0.3.dist-info/top_level.txt
missedSampleLib-0.0.3.dist-info/RECORD
