Metadata-Version: 2.1
Name: missedSampleLib
Version: 0.0.3
Summary: missedSampleLib
Home-page: UNKNOWN
Author: Jordi Tortosa Carreres
Author-email: tortosacarreresjordi@gmail.com
License: UNKNOWN
Keywords: python,missedSampleLib,misidentified samples
Platform: UNKNOWN
Classifier: Programming Language :: Python :: 3
Classifier: Operating System :: OS Independent
License-File: license
